[
  {
    "date": "April 30, 2026",
    "title": "Narasimha Jayanti",
    "time": "1:30 AM - 2:30 AM",
    "description": "Hare Krishna 🙏 Everyone is warmly invited to this evening's weekly program at the Alabama Bhakti Community Center. 🎯 Spring Break Game Night Join us for a relaxed evening of games, association, and prasadam.",
    "menu": [
      {
        "key": "mainItems",
        "label": "Main Items",
        "icon": "🍛",
        "items": [
          "Gauranga Potatoes",
          "Paneer Curry",
          "Quinoa Pulav"
        ]
      },
      {
        "key": "soups",
        "label": "Soups",
        "icon": "🥣",
        "items": [
          "MangoSoup",
          "Sabudana Wada",
          "Raita"
        ]
      },
      {
        "key": "drinks",
        "label": "Fresh & drinks",
        "icon": "🍉",
        "items": [
          "Fruit Salad",
          "Lemonade"
        ]
      }
    ]
  }
]
